__builtins__.pyi
base64.pyi
binascii.pyi
cmath.pyi
copy.pyi
datetime.pyi
deflate.pyi
errno.pyi
fnmatch.pyi
framebuf.pyi
functools.pyi
gc.pyi
gzip.pyi
hashlib.pyi
heapq.pyi
hmac.pyi
html/__init__.pyi
inspect.pyi
itertools.pyi
js.pyi
jsffi.pyi
locale.pyi
logging.pyi
math.pyi
micropython.pyi
mip.pyi
operator.pyi
pathlib.pyi
platform.pyi
pyscript/__init__.pyi
pyscript/fs.pyi
random.pyi
select.pyi
stat.pyi
string.pyi
tarfile/__init__.pyi
tarfile/write.pyi
time.pyi
uarray.pyi
uasyncio.pyi
ubinascii.pyi
ubluetooth.pyi
ucollections.pyi
uctypes.pyi
uerrno.pyi
uhashlib.pyi
uheapq.pyi
uio.pyi
ujson.pyi
umachine.pyi
unittest/__init__.pyi
uos.pyi
uplatform.pyi
urandom.pyi
ure.pyi
uselect.pyi
usocket.pyi
ussl.pyi
ustruct.pyi
usys.pyi
utime.pyi
uu.pyi
uzlib.pyi
vfs.pyi
zlib.pyi
micropython_webassembly_stubs-1.26.0.post2.dist-info/LICENSE.md
micropython_webassembly_stubs-1.26.0.post2.dist-info/METADATA
micropython_webassembly_stubs-1.26.0.post2.dist-info/WHEEL
micropython_webassembly_stubs-1.26.0.post2.dist-info/RECORD
